Metadata-Version: 2.4
Name: abram_text_library
Version: 1.0.0
Summary: A library made by a 10-year-old to print text in cool ways
Author: Abram Jindal
Requires-Dist: rich
Dynamic: author
Dynamic: requires-dist
Dynamic: summary
